Metadata-Version: 1.0
Name: boat-detector
Version: 1.0.0
Summary: Python scripts for detecting noise made by boats in broadband hydrophone data
Home-page: https://gitlab.meridian.cs.dal.ca/data_analytics_dal/packages/boat_detector
Author: Oliver Kirsebom, Fabio Frazao
Author-email: oliver.kirsebom@dal.ca, fsfrazao@dal.ca
License: GNU General Public License v3.0
Platform: UNKNOWN
